gridsmith/__init__.py
gridsmith/api/__init__.py
gridsmith/api/client.py
gridsmith/api/config.py
gridsmith/api/results.py
gridsmith/cli/__init__.py
gridsmith/cli/main.py
gridsmith/core/__init__.py
gridsmith/core/contracts.py
gridsmith/core/eval.py
gridsmith/core/io.py
gridsmith/core/pipelines.py
gridsmith/core/plots.py
gridsmith-0.1.1.dist-info/licenses/LICENSE
gridsmith-0.1.1.dist-info/METADATA
gridsmith-0.1.1.dist-info/WHEEL
gridsmith-0.1.1.dist-info/entry_points.txt
gridsmith-0.1.1.dist-info/top_level.txt
gridsmith-0.1.1.dist-info/RECORD
