Metadata-Version: 2.4
Name: gridsmith
Version: 0.1.1
Summary: Orchestration and reference app layer for ML4U chapter examples
Author: GridSmith Contributors
License: MIT
Classifier: Development Status :: 3 - Alpha
Classifier: Intended Audience :: Developers
Classifier: License :: OSI Approved :: MIT License
Classifier: Programming Language :: Python :: 3
Classifier: Programming Language :: Python :: 3.9
Classifier: Programming Language :: Python :: 3.10
Classifier: Programming Language :: Python :: 3.11
Classifier: Programming Language :: Python :: 3.12
Requires-Python: >=3.9
License-File: LICENSE
Requires-Dist: pandas>=2.0.0
Requires-Dist: numpy>=1.24.0
Requires-Dist: pydantic>=2.0.0
Requires-Dist: typer>=0.9.0
Requires-Dist: pyyaml>=6.0
Requires-Dist: scikit-learn>=1.3.0
Requires-Dist: pyarrow>=10.0.0
Requires-Dist: statsmodels>=0.14.0
Provides-Extra: dev
Requires-Dist: pytest>=7.4.0; extra == "dev"
Requires-Dist: pytest-cov>=4.1.0; extra == "dev"
Requires-Dist: ruff>=0.1.0; extra == "dev"
Requires-Dist: mypy>=1.5.0; extra == "dev"
Provides-Extra: docs
Requires-Dist: sphinx>=7.0.0; extra == "docs"
Requires-Dist: sphinx-rtd-theme>=1.3.0; extra == "docs"
Requires-Dist: myst-parser>=2.0.0; extra == "docs"
Provides-Extra: smith
Requires-Dist: timesmith>=0.1.0; extra == "smith"
Requires-Dist: anomsmith>=0.1.0; extra == "smith"
Requires-Dist: geosmith>=0.1.0; extra == "smith"
Requires-Dist: ressmith>=0.1.0; extra == "smith"
Requires-Dist: plotsmith>=0.1.0; extra == "smith"
Dynamic: license-file
